{
    "concepts": [
        {
            "type": {
                "label": "http://webprotege.stanford.edu/RCxvNxJJgtD9kkphS3bACxj"
            },
            "marker": {
                "type": "OwlEntityMarker",
                "properties": {
                    "dataProperties": {
                        "IndID": "2039"
                    },
                    "objectProperties": {}
                }
            },
            "referent": "GoldUser2039"
        },
        {
            "type": {
                "label": "http://webprotege.stanford.edu/RCQlPYJBbRm4AXOd4O2NjG8"
            },
            "referent": "2",
            "marker": {
                "type": "OwlEntityMarker",
                "properties": {
                    "dataProperties": {
                        "decimalLatitude": "32.492007\u2591",
                        "decimalLongitude": "34.888730\u2591",
                        "locationId": "9"
                    },
                    "objectProperties": {}
                }
            }
        },
        {
            "type": {
                "label": "http://webprotege.stanford.edu/R5QCvjvG51p8PJFre5dv73"
            },
            "marker": {
                "type": "OwlEntityMarker",
                "properties": {
                    "dataProperties": {
                        "has_Obs_ID": "2"
                    },
                    "objectProperties": {
                        "has_Location": {
                            "type_label": "Location",
                            "value": "Location9"
                        }
                    }
                }
            }
        },
        {
            "type": {},
            "referent": "MeasurementValueRhopilema nomadica2"
        },
        {
            "type": {
                "label": "http://webprotege.stanford.edu/RDRKM36qKDuN1Axyn3GeP2T"
            },
            "referent": "MeasurementValue2",
            "marker": {
                "type": "OwlEntityMarker",
                "properties": {
                    "dataProperties": {
                        "original_text": "???? ???? ????? ?? ????? ????? ?????? ????? ??? ???? ?? ????? ?? 500 ?? 1500 ?\\' ?????, ?????? ?????? (????? ?????) ? 5-7 ?????? ?????? ????? ???? ?? ????? ???? ??\\\"?. ?????? ?????? ?????? ????? ??? ?? ?????? ???",
                        "translated_text": "A large swarm of wandering wire and jellyfish is in front of seafood 500 to 1500mm from the beach, maximum density (center of the landing) about 5-7 larger jellyfish and a similar number of smaller ones to the \"K.Beach",
                        "original_language": "he",
                        "translated_language": "en"
                    },
                    "objectProperties": {
                        "has_Location": {
                            "type_label": "Location",
                            "value": "Location9"
                        },
                        "has_measurementValue": {
                            "type_label": "MeasurementValue",
                            "value": "MeasurementValueRhopilema nomadica2"
                        }
                    }
                }
            }
        },
        {
            "type": {
                "label": "http://webprotege.stanford.edu/R7SRsU2VtqcNuMAGVBB5xtm"
            },
            "referent": "Rhopilema nomadica",
            "marker": {
                "type": "OwlEntityMarker",
                "properties": {
                    "dataProperties": {},
                    "objectProperties": {}
                }
            }
        }
    ],
    "relations": [
        {
            "type": {
                "label": "recorded_by"
            },
            "arguments": [
                "2",
                "2039"
            ]
        },
        {
            "type": {
                "label": "observed_during"
            },
            "arguments": [
                "2Rhopilema nomadica",
                "2"
            ]
        },
        {
            "type": {
                "label": "observed_species"
            },
            "arguments": [
                "2Rhopilema nomadica",
                "Rhopilema nomadica"
            ]
        }
    ]
}